Ferment-0.0.1-py2.7-nspkg.pth
ferment/scripts.py
ferment/templates.py
Ferment-0.0.1.dist-info/top_level.txt
Ferment-0.0.1.dist-info/entry_points.txt
Ferment-0.0.1.dist-info/METADATA
Ferment-0.0.1.dist-info/DESCRIPTION.rst
Ferment-0.0.1.dist-info/namespace_packages.txt
Ferment-0.0.1.dist-info/WHEEL
Ferment-0.0.1.dist-info/metadata.json
Ferment-0.0.1.dist-info/RECORD
